{"0": {"home": {"team": "Ampthill", "score": 21, "lineup": [], "events": []}, "away": {"team": "Jersey Reds", "score": 36, "lineup": [], "events": []}, "round": null, "round_type": null, "stadium": null, "date": "2022-09-10T15:00:00+00:00", "attendance": 671}, "1": {"home": {"team": "Cornish Pirates", "score": 21, "lineup": [], "events": []}, "away": {"team": "Richmond", "score": 14, "lineup": [], "events": []}, "round": null, "round_type": null, "stadium": null, "date": "2022-09-10T15:00:00+00:00", "attendance": 1374}, "2": {"home": {"team": "Coventry", "score": 26, "lineup": [], "events": []}, "away": {"team": "Bedford Blues", "score": 18, "lineup": [], "events": []}, "round": null, "round_type": null, "stadium": null, "date": "2022-09-10T15:00:00+00:00", "attendance": 2114}, "3": {"home": {"team": "Ealing Trailfinders", "score": 29, "lineup": [], "events": []}, "away": {"team": "Doncaster Knights", "score": 10, "lineup": [], "events": []}, "round": null, "round_type": null, "stadium": null, "date": "2022-09-10T15:00:00+00:00", "attendance": 868}, "4": {"home": {"team": "London Scottish", "score": 10, "lineup": [], "events": []}, "away": {"team": "Nottingham", "score": 31, "lineup": [], "events": []}, "round": null, "round_type": null, "stadium": null, "date": "2022-09-10T15:00:00+00:00", "attendance": 482}, "5": {"home": {"team": "Hartpury University", "score": 16, "lineup": [], "events": []}, "away": {"team": "Doncaster Knights", "score": 34, "lineup": [], "events": []}, "round": null, "round_type": null, "stadium": null, "date": "2022-09-17T14:30:00+00:00", "attendance": 503}, "6": {"home": {"team": "Ampthill", "score": 17, "lineup": [], "events": []}, "away": {"team": "Ealing Trailfinders", "score": 32, "lineup": [], "events": []}, "round": null, "round_type": null, "stadium": null, "date": "2022-09-17T15:00:00+00:00", "attendance": 565}, "7": {"home": {"team": "Bedford Blues", "score": 49, "lineup": [], "events": []}, "away": {"team": "London Scottish", "score": 36, "lineup": [], "events": []}, "round": null, "round_type": null, "stadium": null, "date": "2022-09-17T15:00:00+00:00", "attendance": 2218}, "8": {"home": {"team": "Jersey Reds", "score": 40, "lineup": [], "events": []}, "away": {"team": "Coventry", "score": 14, "lineup": [], "events": []}, "round": null, "round_type": null, "stadium": null, "date": "2022-09-17T15:00:00+00:00", "attendance": 1112}, "9": {"home": {"team": "Richmond", "score": 32, "lineup": [], "events": []}, "away": {"team": "Caldy", "score": 34, "lineup": [], "events": []}, "round": null, "round_type": null, "stadium": null, "date": "2022-09-17T15:00:00+00:00", "attendance": 685}, "10": {"home": {"team": "Nottingham", "score": 19, "lineup": [], "events": []}, "away": {"team": "Cornish Pirates", "score": 23, "lineup": [], "events": []}, "round": null, "round_type": null, "stadium": null, "date": "2022-09-18T15:00:00+00:00", "attendance": 1057}, "11": {"home": {"team": "London Scottish", "score": 21, "lineup": [], "events": []}, "away": {"team": "Jersey Reds", "score": 55, "lineup": [], "events": []}, "round": null, "round_type": null, "stadium": null, "date": "2022-09-24T14:00:00+00:00", "attendance": 525}, "12": {"home": {"team": "Cornish Pirates", "score": 21, "lineup": [], "events": []}, "away": {"team": "Bedford Blues", "score": 41, "lineup": [], "events": []}, "round": null, "round_type": null, "stadium": null, "date": "2022-09-24T14:30:00+00:00", "attendance": 1491}, "13": {"home": {"team": "Doncaster Knights", "score": 48, "lineup": [], "events": []}, "away": {"team": "Richmond", "score": 24, "lineup": [], "events": []}, "round": null, "round_type": null, "stadium": null, "date": "2022-09-24T14:30:00+00:00", "attendance": 925}, "14": {"home": {"team": "Caldy", "score": 19, "lineup": [], "events": []}, "away": {"team": "Nottingham", "score": 27, "lineup": [], "events": []}, "round": null, "round_type": null, "stadium": null, "date": "2022-09-24T15:00:00+00:00", "attendance": 1125}, "15": {"home": {"team": "Coventry", "score": 26, "lineup": [], "events": []}, "away": {"team": "Ampthill", "score": 24, "lineup": [], "events": []}, "round": null, "round_type": null, "stadium": null, "date": "2022-09-24T15:00:00+00:00", "attendance": 1708}, "16": {"home": {"team": "Ealing Trailfinders", "score": 42, "lineup": [], "events": []}, "away": {"team": "Hartpury University", "score": 7, "lineup": [], "events": []}, "round": null, "round_type": null, "stadium": null, "date": "2022-09-24T15:00:00+00:00", "attendance": 620}, "17": {"home": {"team": "Jersey Reds", "score": 21, "lineup": [], "events": []}, "away": {"team": "Cornish Pirates", "score": 10, "lineup": [], "events": []}, "round": null, "round_type": null, "stadium": null, "date": "2022-09-30T19:15:00+00:00", "attendance": 1385}, "18": {"home": {"team": "Nottingham", "score": 30, "lineup": [], "events": []}, "away": {"team": "Doncaster Knights", "score": 15, "lineup": [], "events": []}, "round": null, "round_type": null, "stadium": null, "date": "2022-09-30T19:15:00+00:00", "attendance": 1130}, "19": {"home": {"team": "Ampthill", "score": 59, "lineup": [], "events": []}, "away": {"team": "London Scottish", "score": 7, "lineup": [], "events": []}, "round": null, "round_type": null, "stadium": null, "date": "2022-10-01T15:00:00+00:00", "attendance": 743}, "20": {"home": {"team": "Bedford Blues", "score": 52, "lineup": [], "events": []}, "away": {"team": "Caldy", "score": 29, "lineup": [], "events": []}, "round": null, "round_type": null, "stadium": null, "date": "2022-10-01T15:00:00+00:00", "attendance": 2584}, "21": {"home": {"team": "Coventry", "score": 5, "lineup": [], "events": []}, "away": {"team": "Ealing Trailfinders", "score": 50, "lineup": [], "events": []}, "round": null, "round_type": null, "stadium": null, "date": "2022-10-01T15:00:00+00:00", "attendance": 2037}, "22": {"home": {"team": "Richmond", "score": 19, "lineup": [], "events": []}, "away": {"team": "Hartpury University", "score": 15, "lineup": [], "events": []}, "round": null, "round_type": null, "stadium": null, "date": "2022-10-01T15:00:00+00:00", "attendance": 475}, "23": {"home": {"team": "Doncaster Knights", "score": 50, "lineup": [], "events": []}, "away": {"team": "Bedford Blues", "score": 19, "lineup": [], "events": []}, "round": null, "round_type": null, "stadium": null, "date": "2022-10-08T14:30:00+00:00", "attendance": 1170}, "24": {"home": {"team": "Hartpury University", "score": 39, "lineup": [], "events": []}, "away": {"team": "Nottingham", "score": 31, "lineup": [], "events": []}, "round": null, "round_type": null, "stadium": null, "date": "2022-10-08T14:30:00+00:00", "attendance": 975}, "25": {"home": {"team": "Caldy", "score": 19, "lineup": [], "events": []}, "away": {"team": "Jersey Reds", "score": 34, "lineup": [], "events": []}, "round": null, "round_type": null, "stadium": null, "date": "2022-10-08T15:00:00+00:00", "attendance": 1895}, "26": {"home": {"team": "Ealing Trailfinders", "score": 56, "lineup": [], "events": []}, "away": {"team": "Richmond", "score": 19, "lineup": [], "events": []}, "round": null, "round_type": null, "stadium": null, "date": "2022-10-08T15:00:00+00:00", "attendance": 1134}, "27": {"home": {"team": "London Scottish", "score": 32, "lineup": [], "events": []}, "away": {"team": "Coventry", "score": 46, "lineup": [], "events": []}, "round": null, "round_type": null, "stadium": null, "date": "2022-10-08T15:00:00+00:00", "attendance": 824}, "28": {"home": {"team": "Cornish Pirates", "score": 15, "lineup": [], "events": []}, "away": {"team": "Ampthill", "score": 13, "lineup": [], "events": []}, "round": null, "round_type": null, "stadium": null, "date": "2022-10-09T14:30:00+00:00", "attendance": 1352}, "29": {"home": {"team": "Jersey Reds", "score": 19, "lineup": [], "events": []}, "away": {"team": "Doncaster Knights", "score": 17, "lineup": [], "events": []}, "round": null, "round_type": null, "stadium": null, "date": "2022-10-21T19:15:00+00:00", "attendance": 1237}, "30": {"home": {"team": "Nottingham", "score": 45, "lineup": [], "events": []}, "away": {"team": "Richmond", "score": 26, "lineup": [], "events": []}, "round": null, "round_type": null, "stadium": null, "date": "2022-10-21T19:45:00+00:00", "attendance": 880}, "31": {"home": {"team": "Ampthill", "score": 26, "lineup": [], "events": []}, "away": {"team": "Caldy", "score": 24, "lineup": [], "events": []}, "round": null, "round_type": null, "stadium": null, "date": "2022-10-22T14:00:00+00:00", "attendance": 683}, "32": {"home": {"team": "Bedford Blues", "score": 28, "lineup": [], "events": []}, "away": {"team": "Hartpury University", "score": 21, "lineup": [], "events": []}, "round": null, "round_type": null, "stadium": null, "date": "2022-10-22T15:00:00+00:00", "attendance": 2429}, "33": {"home": {"team": "Coventry", "score": 32, "lineup": [], "events": []}, "away": {"team": "Cornish Pirates", "score": 19, "lineup": [], "events": []}, "round": null, "round_type": null, "stadium": null, "date": "2022-10-22T15:00:00+00:00", "attendance": 2552}, "34": {"home": {"team": "London Scottish", "score": 21, "lineup": [], "events": []}, "away": {"team": "Ealing Trailfinders", "score": 57, "lineup": [], "events": []}, "round": null, "round_type": null, "stadium": null, "date": "2022-10-22T15:00:00+00:00", "attendance": 674}, "35": {"home": {"team": "Hartpury University", "score": 17, "lineup": [], "events": []}, "away": {"team": "Jersey Reds", "score": 27, "lineup": [], "events": []}, "round": null, "round_type": null, "stadium": null, "date": "2022-10-29T13:30:00+00:00", "attendance": 1035}, "36": {"home": {"team": "Cornish Pirates", "score": 32, "lineup": [], "events": []}, "away": {"team": "London Scottish", "score": 0, "lineup": [], "events": []}, "round": null, "round_type": null, "stadium": null, "date": "2022-10-29T14:30:00+00:00", "attendance": 1564}, "37": {"home": {"team": "Doncaster Knights", "score": 35, "lineup": [], "events": []}, "away": {"team": "Ampthill", "score": 19, "lineup": [], "events": []}, "round": null, "round_type": null, "stadium": null, "date": "2022-10-29T14:30:00+00:00", "attendance": 889}, "38": {"home": {"team": "Caldy", "score": 18, "lineup": [], "events": []}, "away": {"team": "Coventry", "score": 27, "lineup": [], "events": []}, "round": null, "round_type": null, "stadium": null, "date": "2022-10-29T15:00:00+00:00", "attendance": 1100}, "39": {"home": {"team": "Ealing Trailfinders", "score": 64, "lineup": [], "events": []}, "away": {"team": "Nottingham", "score": 33, "lineup": [], "events": []}, "round": null, "round_type": null, "stadium": null, "date": "2022-10-29T15:00:00+00:00", "attendance": 1228}, "40": {"home": {"team": "Richmond", "score": 36, "lineup": [], "events": []}, "away": {"team": "Bedford Blues", "score": 33, "lineup": [], "events": []}, "round": null, "round_type": null, "stadium": null, "date": "2022-10-29T15:00:00+00:00", "attendance": 1324}, "41": {"home": {"team": "Ampthill", "score": 12, "lineup": [], "events": []}, "away": {"team": "Hartpury", "score": 20, "lineup": [], "events": []}, "round": null, "round_type": null, "stadium": null, "date": "2022-12-03T13:30:00+00:00", "attendance": 650}, "42": {"home": {"team": "Cornish Pirates", "score": 12, "lineup": [], "events": []}, "away": {"team": "Ealing Trailfinders", "score": 25, "lineup": [], "events": []}, "round": null, "round_type": null, "stadium": null, "date": "2022-12-03T14:30:00+00:00", "attendance": 1589}, "43": {"home": {"team": "Bedford Blues", "score": 32, "lineup": [], "events": []}, "away": {"team": "Nottingham", "score": 31, "lineup": [], "events": []}, "round": null, "round_type": null, "stadium": null, "date": "2022-12-03T15:00:00+00:00", "attendance": 2491}, "44": {"home": {"team": "Coventry", "score": 47, "lineup": [], "events": []}, "away": {"team": "Doncaster Knights", "score": 7, "lineup": [], "events": []}, "round": null, "round_type": null, "stadium": null, "date": "2022-12-03T15:00:00+00:00", "attendance": 2238}, "45": {"home": {"team": "Jersey Reds", "score": 34, "lineup": [], "events": []}, "away": {"team": "Richmond", "score": 19, "lineup": [], "events": []}, "round": null, "round_type": null, "stadium": null, "date": "2022-12-03T15:00:00+00:00", "attendance": 1074}, "46": {"home": {"team": "London Scottish", "score": 19, "lineup": [], "events": []}, "away": {"team": "Caldy", "score": 10, "lineup": [], "events": []}, "round": null, "round_type": null, "stadium": null, "date": "2022-12-03T15:00:00+00:00", "attendance": 601}, "47": {"home": {"team": "Nottingham", "score": 22, "lineup": [], "events": []}, "away": {"team": "Jersey Reds", "score": 31, "lineup": [], "events": []}, "round": null, "round_type": null, "stadium": null, "date": "2022-12-09T19:45:00+00:00", "attendance": 1100}, "48": {"home": {"team": "Caldy", "score": 15, "lineup": [], "events": []}, "away": {"team": "Cornish Pirates", "score": 14, "lineup": [], "events": []}, "round": null, "round_type": null, "stadium": null, "date": "2022-12-10T14:00:00+00:00", "attendance": 721}, "49": {"home": {"team": "Doncaster Knights", "score": 15, "lineup": [], "events": []}, "away": {"team": "London Scottish", "score": 14, "lineup": [], "events": []}, "round": null, "round_type": null, "stadium": null, "date": "2022-12-10T14:30:00+00:00", "attendance": 922}, "50": {"home": {"team": "Hartpury", "score": 45, "lineup": [], "events": []}, "away": {"team": "Coventry", "score": 36, "lineup": [], "events": []}, "round": null, "round_type": null, "stadium": null, "date": "2022-12-10T14:30:00+00:00", "attendance": 760}, "51": {"home": {"team": "Ealing Trailfinders", "score": 42, "lineup": [], "events": []}, "away": {"team": "Bedford Blues", "score": 17, "lineup": [], "events": []}, "round": null, "round_type": null, "stadium": null, "date": "2022-12-10T15:00:00+00:00", "attendance": 910}, "52": {"home": {"team": "Richmond", "score": 21, "lineup": [], "events": []}, "away": {"team": "Ampthill", "score": 21, "lineup": [], "events": []}, "round": null, "round_type": null, "stadium": null, "date": "2022-12-10T15:00:00+00:00", "attendance": 757}, "55": {"home": {"team": "Jersey Reds", "score": 45, "lineup": [], "events": []}, "away": {"team": "Bedford Blues", "score": 5, "lineup": [], "events": []}, "round": null, "round_type": null, "stadium": null, "date": "2022-12-17T00:00:00+00:00", "attendance": 1090}, "56": {"home": {"team": "Coventry", "score": 48, "lineup": [], "events": []}, "away": {"team": "Richmond", "score": 12, "lineup": [], "events": []}, "round": null, "round_type": null, "stadium": null, "date": "2022-12-17T00:00:00+00:00", "attendance": 2772}, "59": {"home": {"team": "Hartpury", "score": 22, "lineup": [], "events": []}, "away": {"team": "Cornish Pirates", "score": 16, "lineup": [], "events": []}, "round": null, "round_type": null, "stadium": null, "date": "2022-12-23T19:45:00+00:00", "attendance": 960}, "60": {"home": {"team": "Ealing Trailfinders", "score": 43, "lineup": [], "events": []}, "away": {"team": "Jersey Reds", "score": 22, "lineup": [], "events": []}, "round": null, "round_type": null, "stadium": null, "date": "2022-12-24T12:00:00+00:00", "attendance": 1471}, "61": {"home": {"team": "Doncaster Knights", "score": 52, "lineup": [], "events": []}, "away": {"team": "Caldy", "score": 14, "lineup": [], "events": []}, "round": null, "round_type": null, "stadium": null, "date": "2022-12-26T14:30:00+00:00", "attendance": 1125}, "62": {"home": {"team": "Bedford Blues", "score": 38, "lineup": [], "events": []}, "away": {"team": "Ampthill", "score": 14, "lineup": [], "events": []}, "round": null, "round_type": null, "stadium": null, "date": "2022-12-26T15:00:00+00:00", "attendance": 5000}, "63": {"home": {"team": "Nottingham", "score": 17, "lineup": [], "events": []}, "away": {"team": "Coventry", "score": 45, "lineup": [], "events": []}, "round": null, "round_type": null, "stadium": null, "date": "2022-12-26T15:00:00+00:00", "attendance": 1411}, "64": {"home": {"team": "Richmond", "score": 22, "lineup": [], "events": []}, "away": {"team": "London Scottish", "score": 8, "lineup": [], "events": []}, "round": null, "round_type": null, "stadium": null, "date": "2022-12-31T14:30:00+00:00", "attendance": 1898}, "65": {"home": {"team": "Caldy", "score": 26, "lineup": [], "events": []}, "away": {"team": "Ealing Trailfinders", "score": 24, "lineup": [], "events": []}, "round": null, "round_type": null, "stadium": null, "date": "2023-01-07T14:00:00+00:00", "attendance": 1150}, "66": {"home": {"team": "Cornish Pirates", "score": 37, "lineup": [], "events": []}, "away": {"team": "Doncaster Knights", "score": 15, "lineup": [], "events": []}, "round": null, "round_type": null, "stadium": null, "date": "2023-01-07T14:30:00+00:00", "attendance": 1377}, "67": {"home": {"team": "London Scottish", "score": 19, "lineup": [], "events": []}, "away": {"team": "Hartpury", "score": 20, "lineup": [], "events": []}, "round": null, "round_type": null, "stadium": null, "date": "2023-01-07T14:30:00+00:00", "attendance": 430}, "68": {"home": {"team": "Cornish Pirates", "score": 17, "lineup": [], "events": []}, "away": {"team": "Nottingham", "score": 6, "lineup": [], "events": []}, "round": null, "round_type": null, "stadium": null, "date": "2023-01-13T19:30:00+00:00", "attendance": 1460}, "69": {"home": {"team": "Caldy", "score": 27, "lineup": [], "events": []}, "away": {"team": "Richmond", "score": 7, "lineup": [], "events": []}, "round": null, "round_type": null, "stadium": null, "date": "2023-01-14T14:00:00+00:00", "attendance": 1298}, "70": {"home": {"team": "Doncaster Knights", "score": 10, "lineup": [], "events": []}, "away": {"team": "Hartpury", "score": 25, "lineup": [], "events": []}, "round": null, "round_type": null, "stadium": null, "date": "2023-01-14T14:30:00+00:00", "attendance": 948}, "71": {"home": {"team": "Coventry", "score": 19, "lineup": [], "events": []}, "away": {"team": "Jersey Reds", "score": 19, "lineup": [], "events": []}, "round": null, "round_type": null, "stadium": null, "date": "2023-01-14T15:00:00+00:00", "attendance": 3183}, "72": {"home": {"team": "Ealing Trailfinders", "score": 35, "lineup": [], "events": []}, "away": {"team": "Ampthill", "score": 24, "lineup": [], "events": []}, "round": null, "round_type": null, "stadium": null, "date": "2023-01-14T15:00:00+00:00", "attendance": 781}, "73": {"home": {"team": "London Scottish", "score": 13, "lineup": [], "events": []}, "away": {"team": "Bedford Blues", "score": 34, "lineup": [], "events": []}, "round": null, "round_type": null, "stadium": null, "date": "2023-01-14T15:00:00+00:00", "attendance": 700}, "74": {"home": {"team": "Nottingham", "score": 17, "lineup": [], "events": []}, "away": {"team": "Caldy", "score": 29, "lineup": [], "events": []}, "round": null, "round_type": null, "stadium": null, "date": "2023-01-20T19:45:00+00:00", "attendance": 1237}, "76": {"home": {"team": "Hartpury", "score": 13, "lineup": [], "events": []}, "away": {"team": "Ealing Trailfinders", "score": 26, "lineup": [], "events": []}, "round": null, "round_type": null, "stadium": null, "date": "2023-01-21T14:30:00+00:00", "attendance": 980}, "77": {"home": {"team": "Bedford Blues", "score": 55, "lineup": [], "events": []}, "away": {"team": "Cornish Pirates", "score": 13, "lineup": [], "events": []}, "round": null, "round_type": null, "stadium": null, "date": "2023-01-21T15:00:00+00:00", "attendance": 3267}, "78": {"home": {"team": "Jersey Reds", "score": 24, "lineup": [], "events": []}, "away": {"team": "London Scottish", "score": 22, "lineup": [], "events": []}, "round": null, "round_type": null, "stadium": null, "date": "2023-01-21T15:00:00+00:00", "attendance": 1275}, "79": {"home": {"team": "Richmond", "score": 17, "lineup": [], "events": []}, "away": {"team": "Doncaster Knights", "score": 27, "lineup": [], "events": []}, "round": null, "round_type": null, "stadium": null, "date": "2023-01-21T15:00:00+00:00", "attendance": 897}, "80": {"home": {"team": "Caldy", "score": 36, "lineup": [], "events": []}, "away": {"team": "Bedford Blues", "score": 28, "lineup": [], "events": []}, "round": null, "round_type": null, "stadium": null, "date": "2023-01-28T14:00:00+00:00", "attendance": 1875}, "81": {"home": {"team": "Cornish Pirates", "score": 25, "lineup": [], "events": []}, "away": {"team": "Jersey Reds", "score": 34, "lineup": [], "events": []}, "round": null, "round_type": null, "stadium": null, "date": "2023-01-28T14:30:00+00:00", "attendance": 1683}, "82": {"home": {"team": "Doncaster Knights", "score": 32, "lineup": [], "events": []}, "away": {"team": "Nottingham", "score": 17, "lineup": [], "events": []}, "round": null, "round_type": null, "stadium": null, "date": "2023-01-28T14:30:00+00:00", "attendance": 1238}, "83": {"home": {"team": "Hartpury", "score": 26, "lineup": [], "events": []}, "away": {"team": "Richmond", "score": 14, "lineup": [], "events": []}, "round": null, "round_type": null, "stadium": null, "date": "2023-01-28T14:30:00+00:00", "attendance": 376}, "84": {"home": {"team": "Ealing Trailfinders", "score": 19, "lineup": [], "events": []}, "away": {"team": "Coventry", "score": 22, "lineup": [], "events": []}, "round": null, "round_type": null, "stadium": null, "date": "2023-01-28T15:00:00+00:00", "attendance": 987}, "85": {"home": {"team": "London Scottish", "score": 19, "lineup": [], "events": []}, "away": {"team": "Ampthill", "score": 28, "lineup": [], "events": []}, "round": null, "round_type": null, "stadium": null, "date": "2023-01-28T15:00:00+00:00", "attendance": 414}, "86": {"home": {"team": "Ampthill", "score": 36, "lineup": [], "events": []}, "away": {"team": "Nottingham", "score": 24, "lineup": [], "events": []}, "round": null, "round_type": null, "stadium": null, "date": "2023-02-25T14:00:00+00:00", "attendance": 509}, "87": {"home": {"team": "Bedford Blues", "score": 48, "lineup": [], "events": []}, "away": {"team": "Doncaster Knights", "score": 25, "lineup": [], "events": []}, "round": null, "round_type": null, "stadium": null, "date": "2023-03-03T19:45:00+00:00", "attendance": 2585}, "88": {"home": {"team": "Nottingham", "score": 31, "lineup": [], "events": []}, "away": {"team": "Hartpury", "score": 45, "lineup": [], "events": []}, "round": null, "round_type": null, "stadium": null, "date": "2023-03-03T15:00:00+00:00", "attendance": 952}, "89": {"home": {"team": "Ampthill", "score": 22, "lineup": [], "events": []}, "away": {"team": "Cornish Pirates", "score": 61, "lineup": [], "events": []}, "round": null, "round_type": null, "stadium": null, "date": "2023-03-04T14:00:00+00:00", "attendance": 589}, "90": {"home": {"team": "Richmond", "score": 0, "lineup": [], "events": []}, "away": {"team": "Ealing Trailfinders", "score": 50, "lineup": [], "events": []}, "round": null, "round_type": null, "stadium": null, "date": "2023-03-04T14:00:00+00:00", "attendance": 723}, "91": {"home": {"team": "Coventry", "score": 31, "lineup": [], "events": []}, "away": {"team": "London Scottish", "score": 13, "lineup": [], "events": []}, "round": null, "round_type": null, "stadium": null, "date": "2023-03-04T15:00:00+00:00", "attendance": 2745}, "92": {"home": {"team": "Jersey Reds", "score": 71, "lineup": [], "events": []}, "away": {"team": "Caldy", "score": 14, "lineup": [], "events": []}, "round": null, "round_type": null, "stadium": null, "date": "2023-03-04T15:00:00+00:00", "attendance": 1271}, "93": {"home": {"team": "Hartpury", "score": 14, "lineup": [], "events": []}, "away": {"team": "Bedford Blues", "score": 35, "lineup": [], "events": []}, "round": null, "round_type": null, "stadium": null, "date": "2023-03-10T19:45:00+00:00", "attendance": 850}, "94": {"home": {"team": "Cornish Pirates", "score": 31, "lineup": [], "events": []}, "away": {"team": "Coventry", "score": 26, "lineup": [], "events": []}, "round": null, "round_type": null, "stadium": null, "date": "2023-03-11T13:30:00+00:00", "attendance": 1718}, "95": {"home": {"team": "Richmond", "score": 17, "lineup": [], "events": []}, "away": {"team": "Nottingham", "score": 28, "lineup": [], "events": []}, "round": null, "round_type": null, "stadium": null, "date": "2023-03-11T14:00:00+00:00", "attendance": 445}, "97": {"home": {"team": "Caldy", "score": 16, "lineup": [], "events": []}, "away": {"team": "Ampthill", "score": 17, "lineup": [], "events": []}, "round": null, "round_type": null, "stadium": null, "date": "2023-03-11T15:00:00+00:00", "attendance": 657}, "98": {"home": {"team": "Ealing Trailfinders", "score": 66, "lineup": [], "events": []}, "away": {"team": "London Scottish", "score": 0, "lineup": [], "events": []}, "round": null, "round_type": null, "stadium": null, "date": "2023-03-11T15:00:00+00:00", "attendance": 898}, "99": {"home": {"team": "Bedford Blues", "score": 39, "lineup": [], "events": []}, "away": {"team": "Richmond", "score": 5, "lineup": [], "events": []}, "round": null, "round_type": null, "stadium": null, "date": "2023-03-17T19:45:00+00:00", "attendance": 2543}, "100": {"home": {"team": "Coventry", "score": 48, "lineup": [], "events": []}, "away": {"team": "Caldy", "score": 19, "lineup": [], "events": []}, "round": null, "round_type": null, "stadium": null, "date": "2023-03-18T14:00:00+00:00", "attendance": 2407}, "101": {"home": {"team": "Jersey Reds", "score": 36, "lineup": [], "events": []}, "away": {"team": "Hartpury", "score": 22, "lineup": [], "events": []}, "round": null, "round_type": null, "stadium": null, "date": "2023-03-18T14:00:00+00:00", "attendance": 1068}, "102": {"home": {"team": "Nottingham", "score": 21, "lineup": [], "events": []}, "away": {"team": "Ealing Trailfinders", "score": 41, "lineup": [], "events": []}, "round": null, "round_type": null, "stadium": null, "date": "2023-03-18T14:00:00+00:00", "attendance": 1082}, "103": {"home": {"team": "Ampthill", "score": 31, "lineup": [], "events": []}, "away": {"team": "Doncaster Knights", "score": 12, "lineup": [], "events": []}, "round": null, "round_type": null, "stadium": null, "date": "2023-03-18T15:00:00+00:00", "attendance": 407}, "104": {"home": {"team": "London Scottish", "score": 31, "lineup": [], "events": []}, "away": {"team": "Cornish Pirates", "score": 34, "lineup": [], "events": []}, "round": null, "round_type": null, "stadium": null, "date": "2023-03-18T15:00:00+00:00", "attendance": 467}, "105": {"home": {"team": "Hartpury", "score": 26, "lineup": [], "events": []}, "away": {"team": "Ampthill", "score": 32, "lineup": [], "events": []}, "round": null, "round_type": null, "stadium": null, "date": "2023-03-24T19:45:00+00:00", "attendance": 1030}, "106": {"home": {"team": "Richmond", "score": 0, "lineup": [], "events": []}, "away": {"team": "Jersey Reds", "score": 64, "lineup": [], "events": []}, "round": null, "round_type": null, "stadium": null, "date": "2023-03-25T14:00:00+00:00", "attendance": 1153}, "107": {"home": {"team": "Doncaster Knights", "score": 39, "lineup": [], "events": []}, "away": {"team": "Coventry", "score": 45, "lineup": [], "events": []}, "round": null, "round_type": null, "stadium": null, "date": "2023-03-25T14:30:00+00:00", "attendance": 865}, "108": {"home": {"team": "Caldy", "score": 26, "lineup": [], "events": []}, "away": {"team": "London Scottish", "score": 19, "lineup": [], "events": []}, "round": null, "round_type": null, "stadium": null, "date": "2023-03-25T15:00:00+00:00", "attendance": 1895}, "109": {"home": {"team": "Ealing Trailfinders", "score": 50, "lineup": [], "events": []}, "away": {"team": "Cornish Pirates", "score": 12, "lineup": [], "events": []}, "round": null, "round_type": null, "stadium": null, "date": "2023-03-25T15:00:00+00:00", "attendance": 1005}, "110": {"home": {"team": "Nottingham", "score": 26, "lineup": [], "events": []}, "away": {"team": "Bedford Blues", "score": 24, "lineup": [], "events": []}, "round": null, "round_type": null, "stadium": null, "date": "2023-03-26T15:00:00+00:00", "attendance": 871}, "111": {"home": {"team": "Coventry", "score": 42, "lineup": [], "events": []}, "away": {"team": "Hartpury", "score": 19, "lineup": [], "events": []}, "round": null, "round_type": null, "stadium": null, "date": "2023-03-31T19:45:00+00:00", "attendance": 2009}, "112": {"home": {"team": "Ampthill", "score": 33, "lineup": [], "events": []}, "away": {"team": "Richmond", "score": 19, "lineup": [], "events": []}, "round": null, "round_type": null, "stadium": null, "date": "2023-04-01T15:00:00+00:00", "attendance": 547}, "113": {"home": {"team": "Bedford Blues", "score": 31, "lineup": [], "events": []}, "away": {"team": "Ealing Trailfinders", "score": 40, "lineup": [], "events": []}, "round": null, "round_type": null, "stadium": null, "date": "2023-04-01T15:00:00+00:00", "attendance": 2504}, "114": {"home": {"team": "Jersey Reds", "score": 52, "lineup": [], "events": []}, "away": {"team": "Nottingham", "score": 10, "lineup": [], "events": []}, "round": null, "round_type": null, "stadium": null, "date": "2023-04-01T15:00:00+00:00", "attendance": 1242}, "115": {"home": {"team": "London Scottish", "score": 24, "lineup": [], "events": []}, "away": {"team": "Doncaster Knights", "score": 33, "lineup": [], "events": []}, "round": null, "round_type": null, "stadium": null, "date": "2023-04-01T15:00:00+00:00", "attendance": 603}, "116": {"home": {"team": "Cornish Pirates", "score": 28, "lineup": [], "events": []}, "away": {"team": "Caldy", "score": 21, "lineup": [], "events": []}, "round": null, "round_type": null, "stadium": null, "date": "2023-04-02T14:30:00+00:00", "attendance": 1510}, "117": {"home": {"team": "Doncaster Knights", "score": 24, "lineup": [], "events": []}, "away": {"team": "Jersey Reds", "score": 52, "lineup": [], "events": []}, "round": null, "round_type": null, "stadium": null, "date": "2023-04-08T13:00:00+00:00", "attendance": 1007}, "118": {"home": {"team": "Ampthill", "score": 21, "lineup": [], "events": []}, "away": {"team": "Coventry", "score": 45, "lineup": [], "events": []}, "round": null, "round_type": null, "stadium": null, "date": "2023-04-08T14:00:00+00:00", "attendance": 896}, "119": {"home": {"team": "Hartpury", "score": 12, "lineup": [], "events": []}, "away": {"team": "London Scottish", "score": 22, "lineup": [], "events": []}, "round": null, "round_type": null, "stadium": null, "date": "2023-04-14T19:45:00+00:00", "attendance": 258}, "120": {"home": {"team": "Nottingham", "score": 39, "lineup": [], "events": []}, "away": {"team": "Ampthill", "score": 0, "lineup": [], "events": []}, "round": null, "round_type": null, "stadium": null, "date": "2023-04-14T19:45:00+00:00", "attendance": 910}, "121": {"home": {"team": "Doncaster Knights", "score": 13, "lineup": [], "events": []}, "away": {"team": "Cornish Pirates", "score": 14, "lineup": [], "events": []}, "round": null, "round_type": null, "stadium": null, "date": "2023-04-15T14:30:00+00:00", "attendance": 872}, "122": {"home": {"team": "Bedford Blues", "score": 19, "lineup": [], "events": []}, "away": {"team": "Jersey Reds", "score": 26, "lineup": [], "events": []}, "round": null, "round_type": null, "stadium": null, "date": "2023-04-15T15:00:00+00:00", "attendance": 2510}, "123": {"home": {"team": "Ealing Trailfinders", "score": 73, "lineup": [], "events": []}, "away": {"team": "Caldy", "score": 14, "lineup": [], "events": []}, "round": null, "round_type": null, "stadium": null, "date": "2023-04-15T15:00:00+00:00", "attendance": 1031}, "124": {"home": {"team": "Richmond", "score": 18, "lineup": [], "events": []}, "away": {"team": "Coventry", "score": 22, "lineup": [], "events": []}, "round": null, "round_type": null, "stadium": null, "date": "2023-04-15T15:00:00+00:00", "attendance": 990}, "125": {"home": {"team": "Jersey Reds", "score": 19, "lineup": [], "events": []}, "away": {"team": "Ealing Trailfinders", "score": 13, "lineup": [], "events": []}, "round": null, "round_type": null, "stadium": null, "date": "2023-04-22T14:00:00+00:00", "attendance": 3032}, "126": {"home": {"team": "Cornish Pirates", "score": 21, "lineup": [], "events": []}, "away": {"team": "Hartpury", "score": 12, "lineup": [], "events": []}, "round": null, "round_type": null, "stadium": null, "date": "2023-04-22T14:30:00+00:00", "attendance": 1481}, "127": {"home": {"team": "Ampthill", "score": 27, "lineup": [], "events": []}, "away": {"team": "Bedford Blues", "score": 33, "lineup": [], "events": []}, "round": null, "round_type": null, "stadium": null, "date": "2023-04-22T15:00:00+00:00", "attendance": 2600}, "128": {"home": {"team": "Caldy", "score": 7, "lineup": [], "events": []}, "away": {"team": "Doncaster Knights", "score": 38, "lineup": [], "events": []}, "round": null, "round_type": null, "stadium": null, "date": "2023-04-22T15:00:00+00:00", "attendance": 1950}, "129": {"home": {"team": "Coventry", "score": 38, "lineup": [], "events": []}, "away": {"team": "Nottingham", "score": 24, "lineup": [], "events": []}, "round": null, "round_type": null, "stadium": null, "date": "2023-04-22T15:00:00+00:00", "attendance": 3721}, "130": {"home": {"team": "London Scottish", "score": 49, "lineup": [], "events": []}, "away": {"team": "Richmond", "score": 3, "lineup": [], "events": []}, "round": null, "round_type": null, "stadium": null, "date": "2023-04-22T15:00:00+00:00", "attendance": 1622}, "131": {"home": {"team": "Nottingham", "score": 19, "lineup": [], "events": []}, "away": {"team": "London Scottish", "score": 20, "lineup": [], "events": []}, "round": null, "round_type": null, "stadium": null, "date": "2023-04-28T19:45:00+00:00", "attendance": 1782}, "132": {"home": {"team": "Doncaster Knights", "score": 14, "lineup": [], "events": []}, "away": {"team": "Ealing Trailfinders", "score": 35, "lineup": [], "events": []}, "round": null, "round_type": null, "stadium": null, "date": "2023-04-29T14:30:00+00:00", "attendance": 1723}, "133": {"home": {"team": "Bedford Blues", "score": 19, "lineup": [], "events": []}, "away": {"team": "Coventry", "score": 43, "lineup": [], "events": []}, "round": null, "round_type": null, "stadium": null, "date": "2023-04-29T15:00:00+00:00", "attendance": 3256}, "134": {"home": {"team": "Hartpury", "score": 35, "lineup": [], "events": []}, "away": {"team": "Caldy", "score": 13, "lineup": [], "events": []}, "round": null, "round_type": null, "stadium": null, "date": "2023-04-29T15:00:00+00:00", "attendance": 1209}, "135": {"home": {"team": "Jersey Reds", "score": 43, "lineup": [], "events": []}, "away": {"team": "Ampthill", "score": 15, "lineup": [], "events": []}, "round": null, "round_type": null, "stadium": null, "date": "2023-04-29T15:00:00+00:00", "attendance": 2767}, "136": {"home": {"team": "Richmond", "score": 29, "lineup": [], "events": []}, "away": {"team": "Cornish Pirates", "score": 34, "lineup": [], "events": []}, "round": null, "round_type": null, "stadium": null, "date": "2023-04-29T15:00:00+00:00", "attendance": 1042}}